{
  "updatedAt": "2026-01-31T16:10:00-05:00",
  "events": {
    "links": {
      "401810553": "<EVENT_URL>",
      "401810554": "<EVENT_URL>",
      "401810547": "<EVENT_URL>",
      "401810555": "<EVENT_URL>",
      "401810556": "<EVENT_URL>"
    }
  },
  "channels": {
    "links": {
      "espn": "https://lcrj3.envivoslatam.org/espnpremium/tracks-v1a1/mono.m3u8?ip=108.29.21.29&token=9bd484fe9a08d4e894e065b722a88645e15e62e6-3f-1769964985-1769910985",
      "espn2": "<CHANNEL_URL>",
      "tnt": "https://lcrj3.envivoslatam.org/tntsports/tracks-v1a1/mono.m3u8?ip=108.29.21.29&token=78871955623f87352b03d2b0e3ddb3ec96b118b8-59-1769965044-1769911044",
      "nbatv": "https://amg00556-amg00556c3-firetv-us-6060.playouts.now.amagi.tv/playlist720p.m3u8",
      "foxsports": "https://deportes.ksdjugfsddeports.com:9092/MTA4LjI5LjIxLjI5/8_.m3u8?token=Iaorv6-BVReqDlHaTeNJAA&expires=1769952623",
      "univision": "https://streaming-live-fcdn.api.prd.univisionnow.com/wltv/wltv.isml/hls/wltv-audio_eng=128000-video=4000000.m3u8",
      "telemundo": "https://dvrfl03.bozztv.com/hondu-telexitos/tracks-v1a1/mono.ts.m3u8"
    }
  }
}
